netbox_reorder_rack/__init__.py
netbox_reorder_rack/template_content.py
netbox_reorder_rack/urls.py
netbox_reorder_rack/views.py
netbox_reorder_rack/api/__init__.py
netbox_reorder_rack/api/urls.py
netbox_reorder_rack/api/views.py
netbox_reorder_rack/static/netbox_reorder_rack/css/rack.css
netbox_reorder_rack/static/netbox_reorder_rack/js/rack.js
netbox_reorder_rack/static/netbox_reorder_rack/js/rack.js.map
netbox_reorder_rack/templates/netbox_reorder_rack/rack.html
netbox_reorder_rack/templates/netbox_reorder_rack/inc/rack_button.html
netbox_reorder_rack/templates/netbox_reorder_rack/inc/rack_elevation.html
netbox_reorder_rack/templatetags/__init__.py
netbox_reorder_rack/templatetags/rack.py
netbox_reorder_rack/tests/__init__.py
netbox_reorder_rack/tests/test_api.py
netbox_reorder_rack/tests/test_view.py
netbox_reorder_rack-1.1.4.dist-info/licenses/LICENSE
netbox_reorder_rack-1.1.4.dist-info/METADATA
netbox_reorder_rack-1.1.4.dist-info/WHEEL
netbox_reorder_rack-1.1.4.dist-info/top_level.txt
netbox_reorder_rack-1.1.4.dist-info/RECORD
