Metadata-Version: 2.4
Name: netbox_reorder_rack
Version: 1.1.4
Summary: NetBox plugin to reorder rack layouts.
Home-page: https://github.com/minitriga/netbox-reorder-rack/
Author: Alex Gittings
Author-email: agitting96@gmail.com
Project-URL: Bug Tracker, https://github.com/minitriga/netbox-reorder-rack/issues
Classifier: Programming Language :: Python :: 3
Classifier: License :: OSI Approved :: Apache Software License
Classifier: Framework :: Django
License-File: LICENSE
Dynamic: author
Dynamic: author-email
Dynamic: classifier
Dynamic: description
Dynamic: description-content-type
Dynamic: home-page
Dynamic: license-file
Dynamic: project-url
Dynamic: summary
